pic_resizer/__init__.py
pic_resizer/entry.py
pic_resizer/lib.py
pic_resizer/static/favicon.ico
pic_resizer/templates/index.html
pic_resizer/utils.py
pic_resizer/web.py
pic_resizer-0.1.8.dist-info/entry_points.txt
pic_resizer-0.1.8.dist-info/LICENSE
pic_resizer-0.1.8.dist-info/WHEEL
pic_resizer-0.1.8.dist-info/METADATA
pic_resizer-0.1.8.dist-info/RECORD
